aliyunsdkcloud_siem/__init__.py
aliyunsdkcloud_siem/request/__init__.py
aliyunsdkcloud_siem/request/v20220616/AddDataSourceLogRequest.py
aliyunsdkcloud_siem/request/v20220616/AddDataSourceRequest.py
aliyunsdkcloud_siem/request/v20220616/AddUserSourceLogConfigRequest.py
aliyunsdkcloud_siem/request/v20220616/BindAccountRequest.py
aliyunsdkcloud_siem/request/v20220616/CloseDeliveryRequest.py
aliyunsdkcloud_siem/request/v20220616/DeleteAutomateResponseConfigRequest.py
aliyunsdkcloud_siem/request/v20220616/DeleteBindAccountRequest.py
aliyunsdkcloud_siem/request/v20220616/DeleteCustomizeRuleRequest.py
aliyunsdkcloud_siem/request/v20220616/DeleteDataSourceLogRequest.py
aliyunsdkcloud_siem/request/v20220616/DeleteDataSourceRequest.py
aliyunsdkcloud_siem/request/v20220616/DeleteWhiteRuleListRequest.py
aliyunsdkcloud_siem/request/v20220616/DescribeAggregateFunctionRequest.py
aliyunsdkcloud_siem/request/v20220616/DescribeAlertSceneByEventRequest.py
aliyunsdkcloud_siem/request/v20220616/DescribeAlertSceneRequest.py
aliyunsdkcloud_siem/request/v20220616/DescribeAlertSourceRequest.py
aliyunsdkcloud_siem/request/v20220616/DescribeAlertSourceWithEventRequest.py
aliyunsdkcloud_siem/request/v20220616/DescribeAlertTypeRequest.py
aliyunsdkcloud_siem/request/v20220616/DescribeAlertsCountRequest.py
aliyunsdkcloud_siem/request/v20220616/DescribeAlertsRequest.py
aliyunsdkcloud_siem/request/v20220616/DescribeAlertsWithEntityRequest.py
aliyunsdkcloud_siem/request/v20220616/DescribeAlertsWithEventRequest.py
aliyunsdkcloud_siem/request/v20220616/DescribeAuthRequest.py
aliyunsdkcloud_siem/request/v20220616/DescribeAutomateResponseConfigCounterRequest.py
aliyunsdkcloud_siem/request/v20220616/DescribeAutomateResponseConfigFeatureRequest.py
aliyunsdkcloud_siem/request/v20220616/DescribeAutomateResponseConfigPlayBooksRequest.py
aliyunsdkcloud_siem/request/v20220616/DescribeCloudSiemAssetsCounterRequest.py
aliyunsdkcloud_siem/request/v20220616/DescribeCloudSiemAssetsRequest.py
aliyun_python_sdk_cloud_siem-1.0.4.dist-info/LICENSE
aliyun_python_sdk_cloud_siem-1.0.4.dist-info/METADATA
aliyun_python_sdk_cloud_siem-1.0.4.dist-info/WHEEL
aliyun_python_sdk_cloud_siem-1.0.4.dist-info/top_level.txt
aliyun_python_sdk_cloud_siem-1.0.4.dist-info/RECORD
